MANIFEST.in
README.rst
setup.py
docs/HISTORY.rst
docs/INSTALL.txt
docs/LICENSE.GPL
docs/LICENSE.txt
zopyx/__init__.py
zopyx.ipsumplone.egg-info/PKG-INFO
zopyx.ipsumplone.egg-info/SOURCES.txt
zopyx.ipsumplone.egg-info/dependency_links.txt
zopyx.ipsumplone.egg-info/entry_points.txt
zopyx.ipsumplone.egg-info/namespace_packages.txt
zopyx.ipsumplone.egg-info/not-zip-safe
zopyx.ipsumplone.egg-info/requires.txt
zopyx.ipsumplone.egg-info/top_level.txt
zopyx/ipsumplone/__init__.py
zopyx/ipsumplone/configure.zcml
zopyx/ipsumplone/profiles.zcml
zopyx/ipsumplone/setuphandlers.py
zopyx/ipsumplone/skins.zcml
zopyx/ipsumplone/version.txt
zopyx/ipsumplone/browser/__init__.py
zopyx/ipsumplone/browser/configure.zcml
zopyx/ipsumplone/browser/demo.pdf
zopyx/ipsumplone/browser/interfaces.py
zopyx/ipsumplone/browser/setup.py
zopyx/ipsumplone/profiles/default/zopyx.ipsumplone_various.txt
zopyx/ipsumplone/profiles/uninstall/readme.txt