Metadata-Version: 1.1
Name: zopyx.ipsumplone
Version: 0.4.1
Summary: Lorem ipsum text and image demo content for Plone
Home-page: http://pypi.python.org/pypi/zopyx.ipsumplone
Author: Andreas Jung
Author-email: info@zopyx.com
License: GPL
Keywords: Plone Loremipsum
Platform: UNKNOWN
Classifier: Framework :: Plone
Classifier: Framework :: Plone :: 5.2
Classifier: Framework :: Plone :: 6.0
Classifier: Programming Language :: Python
